vaas/__init__.py
vaas/_version.py
vaas/fx/fx_model.py
vaas/fx/fx_utils.py
vaas/hsm/hybrid_score.py
vaas/inference/__init__.py
vaas/inference/pipeline.py
vaas/inference/utils.py
vaas/inference/visualize.py
vaas/px/px_model.py
vaas/px/px_utils.py
vaas/utils/helpers.py
vaas/utils/losses.py
vaas/utils/metrics.py
vaas/utils/seed.py
vaas-0.1.7.dist-info/licenses/LICENSE
vaas-0.1.7.dist-info/METADATA
vaas-0.1.7.dist-info/WHEEL
vaas-0.1.7.dist-info/top_level.txt
vaas-0.1.7.dist-info/RECORD
