Metadata-Version: 2.4
Name: vaas
Version: 0.1.7
Summary: VAAS (Vision-Attention Anomaly Scoring) is a dual-module vision framework for image anomaly detection and localisation.
Author: Opeyemi Bamigbade, Mark Scanlon, John Sheppard
Requires-Python: >=3.10
License-File: LICENSE
Requires-Dist: transformers>=4.40
Requires-Dist: numpy
Requires-Dist: pillow
Requires-Dist: tqdm
Requires-Dist: scipy
Requires-Dist: opencv-python-headless
Requires-Dist: matplotlib>=3.10.8
Dynamic: license-file
